flask_automate_docs/__init__.py
flask_automate_docs/generator.py
flask_automate_docs/integration.py
flask_automate_docs-0.1.0.dist-info/METADATA
flask_automate_docs-0.1.0.dist-info/WHEEL
flask_automate_docs-0.1.0.dist-info/top_level.txt
flask_automate_docs-0.1.0.dist-info/RECORD
