Metadata-Version: 2.4
Name: flask-automate-docs
Version: 0.1.0
Summary: A Flask extension for automatic API documentation generation
Home-page: https://github.com/Gowtham2005-2005/flask-automate-docs
Author: Gowtham
Author-email: gowtham2005@gmail.com
Classifier: Development Status :: 3 - Alpha
Classifier: Intended Audience :: Developers
Classifier: License :: OSI Approved :: MIT License
Classifier: Programming Language :: Python :: 3
Classifier: Programming Language :: Python :: 3.7
Classifier: Programming Language :: Python :: 3.8
Classifier: Programming Language :: Python :: 3.9
Classifier: Programming Language :: Python :: 3.10
Classifier: Programming Language :: Python :: 3.11
Requires-Python: >=3.7
Requires-Dist: flask>=2.0.0
Requires-Dist: flask-sqlalchemy>=3.0.0
Dynamic: author
Dynamic: author-email
Dynamic: classifier
Dynamic: description
Dynamic: description-content-type
Dynamic: home-page
Dynamic: requires-dist
Dynamic: requires-python
Dynamic: summary
